validator_entrypoint.py
validator_devel/__init__.py
validator_devel/__main__.py
validator_devel/filesystem.py
validator_devel/main.py
validator_devel/routes.py
validator_devel/stu3_base.html.j2
validator_devel/templating.py
validator_devel/views.py
validator_devel/appoggio/img/Etichetta.jpg
validator_devel/appoggio/img/MarcaDaBollo.jpg
validator_devel/appoggio/img/RL.gif
validator_devel/appoggio/img/RL.png
validator_devel/appoggio/img/Stemma.jpg
validator_devel/appoggio/img/StemmaComune.jpg
validator_devel/appoggio/img/StemmaComune.png
validator_devel/appoggio/img/carica_campi.png
validator_devel/appoggio/img/caso1.jpg
validator_devel/appoggio/img/caso2.jpg
validator_devel/appoggio/img/caso3.jpg
validator_devel/appoggio/img/caso4.jpg
validator_devel/appoggio/img/caso5.jpg
validator_devel/appoggio/img/download-pdf.png
validator_devel/appoggio/img/download.ico
validator_devel/appoggio/img/download.png
validator_devel/appoggio/img/edit.png
validator_devel/appoggio/img/favicon.ico
validator_devel/appoggio/img/file.png
validator_devel/appoggio/img/folder-closed.png
validator_devel/appoggio/img/folder.png
validator_devel/appoggio/img/glyphicons-halflings-white.png
validator_devel/appoggio/img/glyphicons-halflings.png
validator_devel/appoggio/img/help.png
validator_devel/appoggio/img/logo_globo.png
validator_devel/appoggio/img/mappa.png
validator_devel/appoggio/img/pdf.png
validator_devel/appoggio/img/spinner.gif
validator_devel/appoggio/img/tick.png
validator_devel/appoggio/img/upload.png
validator_devel/appoggio/img/valida.png
validator_devel/appoggio/img/warning.png
validator_devel/appoggio/img/icon/address_book.png
validator_devel/appoggio/img/icon/adjust.png
validator_devel/appoggio/img/icon/adjust_alt.png
validator_devel/appoggio/img/icon/airplane.png
validator_devel/appoggio/img/icon/alarm.png
validator_devel/appoggio/img/icon/albums.png
validator_devel/appoggio/img/icon/align_center.png
validator_devel/appoggio/img/icon/align_left.png
maggioli_validator_devel-2.1.3.dist-info/METADATA
maggioli_validator_devel-2.1.3.dist-info/WHEEL
maggioli_validator_devel-2.1.3.dist-info/entry_points.txt
maggioli_validator_devel-2.1.3.dist-info/top_level.txt
maggioli_validator_devel-2.1.3.dist-info/RECORD
