Metadata-Version: 2.1
Name: maggioli-validator-devel
Version: 2.1.3
Summary: Management utilities for Maggioli's Sportello Telematico modules
Author: Gruppo Maggioli
Classifier: Programming Language :: Python :: 3
Classifier: License :: OSI Approved :: MIT License
Classifier: Operating System :: OS Independent
Requires-Dist: PyYAML (==6.0)
Requires-Dist: argh (==0.26.2)
Requires-Dist: pathtools (==0.1.2)
Requires-Dist: aiohttp (==3.8.3)
Requires-Dist: watchdog (==2.2.0)
Requires-Dist: Jinja2 (==3.1.2)
Requires-Dist: dynaconf (==3.1.11)
Requires-Dist: Click (==8.1.3)
Requires-Dist: bs4 (==0.0.1)
Requires-Dist: requests (==2.28.1)
